[{"model": "app_product.tag", "pk": 1, "fields": {"name": "Noise reduction", "category": 2, "products": [1]}}, {"model": "app_product.tag", "pk": 2, "fields": {"name": "Case included", "category": 2, "products": [1]}}, {"model": "app_product.tag", "pk": 3, "fields": {"name": "Apple", "category": 7, "products": [2]}}, {"model": "app_product.tag", "pk": 4, "fields": {"name": "BBK", "category": 5, "products": [3]}}, {"model": "app_product.tag", "pk": 5, "fields": {"name": "Built-in grill", "category": 5, "products": [3, 7, 9]}}, {"model": "app_product.tag", "pk": 6, "fields": {"name": "Enamel coating", "category": 5, "products": [3]}}, {"model": "app_product.tag", "pk": 7, "fields": {"name": "Limited", "category": 5, "products": [3, 4, 5, 6, 10]}}, {"model": "app_product.tag", "pk": 8, "fields": {"name": "Focal", "category": 2, "products": [5]}}, {"model": "app_product.tag", "pk": 9, "fields": {"name": "Premium", "category": 2, "products": [5, 8, 11, 14, 17]}}, {"model": "app_product.tag", "pk": 10, "fields": {"name": "Accesstyle", "category": 5, "products": [7]}}, {"model": "app_product.tag", "pk": 11, "fields": {"name": "Rekam", "category": 3, "products": [10]}}, {"model": "app_product.tag", "pk": 12, "fields": {"name": "Mini", "category": 3, "products": [12]}}, {"model": "app_product.tag", "pk": 13, "fields": {"name": "Rondell", "category": 6, "products": [13]}}, {"model": "app_product.tag", "pk": 14, "fields": {"name": "Scarlett", "category": 6, "products": [14]}}, {"model": "app_product.tag", "pk": 15, "fields": {"name": "Leben", "category": 6, "products": [15]}}, {"model": "app_product.tag", "pk": 16, "fields": {"name": "Infinix", "category": 7, "products": [16]}}]